[
	{
		"name": "Шапка-&gt;GlobalHeader",
		"id": "ida4ac7283-718b-40e2-ebf3-fa732868af1b",
		"isDone": false,
		"comment": "",
		"priority": 1,
		"weight": {
			"done": 0,
			"all": 12
		},
		"children": [
			{
				"name": "Шапка Экстерновская (сервисы, личный кабинет, выход)",
				"id": "ida6a46fc1-29f6-4c12-5de1-62bf6b37bc2b",
				"isDone": false,
				"comment": "",
				"priority": 0,
				"weight": {
					"done": 0,
					"all": 1
				}
			},
			{
				"name": "Шапка НДФЛ (настройки, помощь и пр)-&gt;NDFLHeader",
				"id": "idf0cae8e1-54c5-4e75-db67-4efa55ddb549",
				"isDone": false,
				"comment": "",
				"priority": 0,
				"weight": {
					"done": 0,
					"all": 11
				},
				"children": [
					{
						"name": "Переход в КЭ",
						"id": "id5a1a7712-b4d1-4a82-e1f2-574aef0144c6",
						"isDone": false,
						"comment": "",
						"priority": 0,
						"weight": {
							"done": 0,
							"all": 1
						}
					},
					{
						"name": "Смена организаций-&gt;ChangeOrganization",
						"id": "id9e44697f-a153-4fe4-cf6f-df1df9210c00",
						"isDone": false,
						"comment": "",
						"priority": 0,
						"weight": {
							"done": 0,
							"all": 1
						}
					},
					{
						"name": "ИНН-КПП организации",
						"id": "idb78c2dca-f4ad-4bb5-95cc-14684ec0fc7f",
						"isDone": false,
						"comment": "",
						"priority": 0,
						"weight": {
							"done": 0,
							"all": 1
						}
					},
					{
						"name": "Реквизиты и настройки-&gt;RequisitesAndPreferences",
						"id": "idabe1cb15-c62c-479c-7364-2cfe73e751a4",
						"isDone": false,
						"comment": "",
						"priority": 0,
						"weight": {
							"done": 0,
							"all": 2
						},
						"children": [
							{
								"name": "Реквизиты плательщика",
								"id": "ide32cbc1c-a2c2-4d04-42a9-68a4b3aa94a1",
								"isDone": false,
								"comment": "",
								"priority": 0,
								"weight": {
									"done": 0,
									"all": 1
								}
							},
							{
								"name": "Сообщение о представительстве",
								"id": "id6765b523-865f-4b89-f93c-56a1531f8487",
								"isDone": false,
								"comment": "",
								"priority": 0,
								"weight": {
									"done": 0,
									"all": 1
								}
							}
						]
					},
					{
						"name": "Помощь-&gt;GlobalHelpLink  box",
						"id": "idc332bd11-dbca-47fc-0ee0-4809e92d4410",
						"isDone": false,
						"comment": "",
						"priority": 0,
						"weight": {
							"done": 0,
							"all": 6
						},
						"children": [
							{
								"name": "Номер Call-центра",
								"id": "id61fee62a-b832-4beb-d485-2c95d5a0599e",
								"isDone": false,
								"comment": "",
								"priority": 0,
								"weight": {
									"done": 0,
									"all": 1
								}
							},
							{
								"name": "Диагностика",
								"id": "id462c6502-9da0-4129-ec2b-921756c163e1",
								"isDone": false,
								"comment": "",
								"priority": 0,
								"weight": {
									"done": 0,
									"all": 1
								}
							},
							{
								"name": "Дистанционная помощь",
								"id": "idfcc16922-9250-4271-999d-20648c140958",
								"isDone": false,
								"comment": "",
								"priority": 0,
								"weight": {
									"done": 0,
									"all": 1
								}
							},
							{
								"name": "Перенос справок из старого сервиса",
								"id": "idd9d0493a-a2b8-4425-0630-477b027c8ab6",
								"isDone": false,
								"comment": "",
								"priority": 0,
								"weight": {
									"done": 0,
									"all": 1
								}
							},
							{
								"name": "Видео про заполнение отчёта",
								"id": "id359e8d48-2ac8-47b5-8ec6-c49c099987ea",
								"isDone": false,
								"comment": "",
								"priority": 0,
								"weight": {
									"done": 0,
									"all": 1
								}
							},
							{
								"name": "Видео про импорт отчёта",
								"id": "id2ef755a2-ac84-417f-3ce3-540cb0523837",
								"isDone": false,
								"comment": "",
								"priority": 0,
								"weight": {
									"done": 0,
									"all": 1
								}
							}
						]
					}
				]
			}
		]
	},
	{
		"name": "Список и прочее-&gt;InquiryListPage",
		"id": "id08d0a7bc-f5b6-4692-ec6a-89ad217faf9b",
		"isDone": false,
		"comment": "",
		"priority": 0,
		"weight": {
			"done": 0,
			"all": 42
		},
		"children": [
			{
				"name": "Шапка с реквизитами-&gt;PageHeader",
				"id": "ide9167a27-3e67-459e-5697-f75a4e29324e",
				"isDone": false,
				"comment": "",
				"priority": 0,
				"weight": {
					"done": 0,
					"all": 13
				},
				"children": [
					{
						"name": "Год",
						"id": "id8986f635-0e59-430a-badd-a1a25a6f9230",
						"isDone": false,
						"comment": "",
						"priority": 0,
						"weight": {
							"done": 0,
							"all": 1
						}
					},
					{
						"name": "Формат",
						"id": "idf7b9a5e8-a7f0-4706-aca9-b7265bc800de",
						"isDone": false,
						"comment": "",
						"priority": 0,
						"weight": {
							"done": 0,
							"all": 1
						}
					},
					{
						"name": "Реквизиты",
						"id": "id4046b848-b87e-49cc-c51c-02f030da2b87",
						"isDone": false,
						"comment": "",
						"priority": 0,
						"weight": {
							"done": 0,
							"all": 1
						}
					},
					{
						"name": "Редактирование реквизитов-&gt;Requisites",
						"id": "id536dc195-d95c-457f-5550-d7f10fcc4bd9",
						"isDone": false,
						"comment": "",
						"priority": 0,
						"weight": {
							"done": 0,
							"all": 10
						},
						"children": [
							{
								"name": "Валидации на ссылке «Изменить»",
								"id": "id0d0b77c7-51ea-49ca-6ab2-c880452457b2",
								"isDone": false,
								"comment": "",
								"priority": 0,
								"weight": {
									"done": 0,
									"all": 1
								}
							},
							{
								"name": "Лайтбокс-&gt;EditRequisitesLightbox",
								"id": "ida52d3339-fcb5-4691-8011-99f17e86923e",
								"isDone": false,
								"comment": "",
								"priority": 0,
								"weight": {
									"done": 0,
									"all": 9
								},
								"children": [
									{
										"name": "Поля общие-&gt;CommonRequisites",
										"id": "idf64b696a-eef9-4692-689e-3e420570201b",
										"isDone": false,
										"comment": "",
										"priority": 0,
										"weight": {
											"done": 0,
											"all": 6
										},
										"children": [
											{
												"name": "ИФНС/МРИ",
												"id": "id37380753-01c4-4522-bd66-6719f9c6b7bc",
												"isDone": false,
												"comment": "",
												"priority": 0,
												"weight": {
													"done": 0,
													"all": 1
												}
											},
											{
												"name": "ОКТМО",
												"id": "idbcb969c4-0892-4a7b-585c-a20968fcc453",
												"isDone": false,
												"comment": "",
												"priority": 0,
												"weight": {
													"done": 0,
													"all": 1
												}
											},
											{
												"name": "ИНН",
												"id": "idcad4edff-207e-45db-ca46-69d2c33dde18",
												"isDone": false,
												"comment": "",
												"priority": 0,
												"weight": {
													"done": 0,
													"all": 1
												}
											},
											{
												"name": "КПП",
												"id": "idc5b53df7-7bc7-43c9-948f-9a046af71214",
												"isDone": false,
												"comment": "",
												"priority": 0,
												"weight": {
													"done": 0,
													"all": 1
												}
											},
											{
												"name": "Наименование организации",
												"id": "id9078486c-0769-44e5-9e5d-24e40a142359",
												"isDone": false,
												"comment": "",
												"priority": 0,
												"weight": {
													"done": 0,
													"all": 1
												}
											},
											{
												"name": "Телефон",
												"id": "id4c7368dc-ef27-46c3-c4f4-447ebc2a20f8",
												"isDone": false,
												"comment": "",
												"priority": 0,
												"weight": {
													"done": 0,
													"all": 1
												}
											}
										]
									},
									{
										"name": "Поля 5.04-&gt;Format504Requisitest",
										"id": "id7b4f332a-72ae-448b-ec8c-03bdd11d2dcf",
										"isDone": false,
										"comment": "",
										"priority": 0,
										"weight": {
											"done": 0,
											"all": 2
										},
										"children": [
											{
												"name": "Руководитель (ФИО)",
												"id": "idac756a29-5742-451d-bbdb-ac3ab1a5039e",
												"isDone": false,
												"comment": "",
												"priority": 0,
												"weight": {
													"done": 0,
													"all": 1
												}
											},
											{
												"name": "Признак подписанта",
												"id": "idd48e2b43-282d-4c12-a736-a9eca53a5262",
												"isDone": false,
												"comment": "",
												"priority": 0,
												"weight": {
													"done": 0,
													"all": 1
												}
											}
										]
									},
									{
										"name": "Поведение лайтбокса",
										"id": "ida9858f23-2347-4a67-92be-ded33d74b12d",
										"isDone": false,
										"comment": "",
										"priority": 0,
										"weight": {
											"done": 0,
											"all": 1
										}
									}
								]
							}
						]
					}
				]
			},
			{
				"name": "Шапка с действиями ActionsHeader",
				"id": "id9f507640-b9e2-4eea-7f72-b108d5a8bbf8",
				"isDone": false,
				"comment": "",
				"priority": 0,
				"weight": {
					"done": 0,
					"all": 16
				},
				"children": [
					{
						"name": "Чекбокс",
						"id": "idd7ea1955-cf9b-4726-3a11-0b3d0b31ba83",
						"isDone": false,
						"comment": "",
						"priority": 0,
						"weight": {
							"done": 0,
							"all": 1
						}
					},
					{
						"name": "Создать справку",
						"id": "id166736d2-9ed4-4855-5aa0-4d4b48293827",
						"isDone": false,
						"comment": "",
						"priority": 0,
						"weight": {
							"done": 0,
							"all": 1
						}
					},
					{
						"name": "Действия-&gt;Actions",
						"id": "id4529f6b7-297b-4452-6564-00062845426c",
						"isDone": false,
						"comment": "",
						"priority": 0,
						"weight": {
							"done": 0,
							"all": 1
						}
					},
					{
						"name": "Общие CommonActions",
						"id": "id30a1f3d1-ae0e-452d-7f2d-1e224bfa60f9",
						"isDone": false,
						"comment": "",
						"priority": 0,
						"weight": {
							"done": 0,
							"all": 1
						},
						"children": [
							{
								"name": "Импорт",
								"id": "ide1e1a777-f980-4f4f-4908-78150c0dd63a",
								"isDone": false,
								"comment": "",
								"priority": 0,
								"weight": {
									"done": 0,
									"all": 1
								}
							}
						]
					},
					{
						"name": "Для выбранных справок-&gt;CheckedInquiriesActions",
						"id": "id464ca177-35f0-4118-4437-fbe08c51b4af",
						"isDone": false,
						"comment": "",
						"priority": 0,
						"weight": {
							"done": 0,
							"all": 6
						},
						"children": [
							{
								"name": "Перенумеровать",
								"id": "idbc1636e8-fe36-4378-3d6c-6c19bea20189",
								"isDone": false,
								"comment": "",
								"priority": 0,
								"weight": {
									"done": 0,
									"all": 1
								}
							},
							{
								"name": "Включить авторасчет общих сумм налога и дохода",
								"id": "id939a4c51-6c94-4835-2399-f20326d4fcab",
								"isDone": false,
								"comment": "",
								"priority": 0,
								"weight": {
									"done": 0,
									"all": 1
								}
							},
							{
								"name": "Изменить тип справок",
								"id": "id5b74f7d8-0676-4cf4-0b8f-048cb59a9b1a",
								"isDone": false,
								"comment": "",
								"priority": 0,
								"weight": {
									"done": 0,
									"all": 1
								}
							},
							{
								"name": "Напечатать справки",
								"id": "id5929b834-a6db-4059-85f7-34c2f6baeeaf",
								"isDone": false,
								"comment": "",
								"priority": 0,
								"weight": {
									"done": 0,
									"all": 1
								}
							},
							{
								"name": "Напечатать реестр",
								"id": "id407824bb-3809-4281-18fe-277e04d36b05",
								"isDone": false,
								"comment": "",
								"priority": 0,
								"weight": {
									"done": 0,
									"all": 1
								}
							},
							{
								"name": "Удалить",
								"id": "ide11602aa-84c1-4dfb-c2f4-d2ac7986642c",
								"isDone": false,
								"comment": "",
								"priority": 0,
								"weight": {
									"done": 0,
									"all": 1
								}
							}
						]
					},
					{
						"name": "Фильтр PersonSampling",
						"id": "id3ae10041-2d40-4ea8-79a1-be0ba6c59461",
						"isDone": false,
						"comment": "",
						"priority": 0,
						"weight": {
							"done": 0,
							"all": 5
						},
						"children": [
							{
								"name": "Все справки",
								"id": "ida5456644-7797-4b9c-cc3d-579d189af684",
								"isDone": false,
								"comment": "",
								"priority": 0,
								"weight": {
									"done": 0,
									"all": 1
								}
							},
							{
								"name": "По удержанному НДФЛ",
								"id": "id35bd5649-1440-4605-3108-5ceb41a1f636",
								"isDone": false,
								"comment": "",
								"priority": 0,
								"weight": {
									"done": 0,
									"all": 1
								}
							},
							{
								"name": "По неудержанному НДФЛ",
								"id": "id94d0bb11-dca4-4c4f-fac2-b757d0dbc330",
								"isDone": false,
								"comment": "",
								"priority": 0,
								"weight": {
									"done": 0,
									"all": 1
								}
							},
							{
								"name": "Выбранные справки",
								"id": "id606858e1-616d-49d8-e89d-2fa6cc86b2e7",
								"isDone": false,
								"comment": "",
								"priority": 0,
								"weight": {
									"done": 0,
									"all": 1
								}
							},
							{
								"name": "С ошибками/предупреждениями",
								"id": "idd6002d2f-80e3-455c-98a6-89d2f41051f2",
								"isDone": false,
								"comment": "",
								"priority": 0,
								"weight": {
									"done": 0,
									"all": 1
								}
							}
						]
					},
					{
						"name": "Поиск",
						"id": "id49811f66-2d05-4418-fb20-1ea5bb4d252f",
						"isDone": false,
						"comment": "",
						"priority": 0,
						"weight": {
							"done": 0,
							"all": 1
						}
					}
				]
			},
			{
				"name": "Список-&gt;InquiryList",
				"id": "id518cdc8f-669c-4e0f-b69f-57973dbf3d1c",
				"isDone": false,
				"comment": "",
				"priority": 0,
				"weight": {
					"done": 0,
					"all": 8
				},
				"children": [
					{
						"name": "Чекбокс",
						"id": "id0c97c4cd-8740-4449-d389-23c5fe4a965b",
						"isDone": false,
						"comment": "",
						"priority": 0,
						"weight": {
							"done": 0,
							"all": 1
						}
					},
					{
						"name": "Номер",
						"id": "id79101678-56d3-45cf-83f4-fe47233257e8",
						"isDone": false,
						"comment": "",
						"priority": 0,
						"weight": {
							"done": 0,
							"all": 1
						}
					},
					{
						"name": "ФИО",
						"id": "idf4d9fea4-5612-4392-fdd0-3ae6f9031fe0",
						"isDone": false,
						"comment": "",
						"priority": 0,
						"weight": {
							"done": 0,
							"all": 1
						}
					},
					{
						"name": "Валилации",
						"id": "idcfdeb487-f278-4e68-650e-7e968615043f",
						"isDone": false,
						"comment": "",
						"priority": 0,
						"weight": {
							"done": 0,
							"all": 1
						}
					},
					{
						"name": "Суммы-&gt;InquiryListSums",
						"id": "idc0de35bc-8713-401f-dc69-be210a61669b",
						"isDone": false,
						"comment": "",
						"priority": 0,
						"weight": {
							"done": 0,
							"all": 4
						},
						"children": [
							{
								"name": "Дохода",
								"id": "ida5aad588-1dad-4e8e-9f3b-2cdc623ec58a",
								"isDone": false,
								"comment": "",
								"priority": 0,
								"weight": {
									"done": 0,
									"all": 1
								}
							},
							{
								"name": "Исчислено",
								"id": "idb7c74c2c-40f2-4e57-d7d8-17455226f4a2",
								"isDone": false,
								"comment": "",
								"priority": 0,
								"weight": {
									"done": 0,
									"all": 1
								}
							},
							{
								"name": "Удержано",
								"id": "id8d7cc54c-de35-418a-d7cf-62f8011c7412",
								"isDone": false,
								"comment": "",
								"priority": 0,
								"weight": {
									"done": 0,
									"all": 1
								}
							},
							{
								"name": "Перечислено",
								"id": "id518c6e62-52ad-482e-fd7e-fcdd015d4a01",
								"isDone": false,
								"comment": "",
								"priority": 0,
								"weight": {
									"done": 0,
									"all": 1
								}
							}
						]
					}
				]
			},
			{
				"name": "Футтер-&gt;InquiryListFooter",
				"id": "idd0e808e9-34e3-40af-a387-3abc345f572a",
				"isDone": false,
				"comment": "",
				"priority": 0,
				"weight": {
					"done": 0,
					"all": 5
				},
				"children": [
					{
						"name": "Проверить и отправить отчёт-&gt;SendReportButton",
						"id": "id13894408-7acd-46f1-261b-f0ff468357af",
						"isDone": false,
						"comment": "",
						"priority": 0,
						"weight": {
							"done": 0,
							"all": 1
						}
					},
					{
						"name": "Итоговые суммы-&gt;CommonSums",
						"id": "id1bfaf0ed-50a8-4e1e-4d1d-8c1eba692104",
						"isDone": false,
						"comment": "",
						"priority": 0,
						"weight": {
							"done": 0,
							"all": 4
						},
						"children": [
							{
								"name": "Дохода",
								"id": "ide30f0cc9-0b73-4ae6-2a43-b124ce27053b",
								"isDone": false,
								"comment": "",
								"priority": 0,
								"weight": {
									"done": 0,
									"all": 1
								}
							},
							{
								"name": "Исчислено",
								"id": "id278b684e-b4e8-4973-9ee4-c60698e9060b",
								"isDone": false,
								"comment": "",
								"priority": 0,
								"weight": {
									"done": 0,
									"all": 1
								}
							},
							{
								"name": "Удержано",
								"id": "idcd370873-f5b8-4169-03b1-ba9cd23339ef",
								"isDone": false,
								"comment": "",
								"priority": 0,
								"weight": {
									"done": 0,
									"all": 1
								}
							},
							{
								"name": "Перечислено",
								"id": "id78f19466-84f5-4d47-7efe-06a90c0dccc9",
								"isDone": false,
								"comment": "",
								"priority": 0,
								"weight": {
									"done": 0,
									"all": 1
								}
							}
						]
					}
				]
			}
		]
	},
	{
		"name": "Справка на редактировании-&gt;InquiryPage",
		"id": "ida48f223c-dfdb-4310-f042-250f32be4c1a",
		"isDone": false,
		"comment": "",
		"priority": 0,
		"weight": {
			"done": 0,
			"all": 51
		},
		"children": [
			{
				"name": "Инфо о справке + действия-&gt;InquiryRequisites",
				"id": "id31cbe1cc-a6a2-4f70-8aab-fd4d24271cc2",
				"isDone": false,
				"comment": "",
				"priority": 0,
				"weight": {
					"done": 0,
					"all": 13
				},
				"children": [
					{
						"name": "Реквизиты справки:",
						"id": "id6b570397-32e8-4454-c048-61b77e2189ca",
						"isDone": false,
						"comment": "",
						"priority": 0,
						"weight": {
							"done": 0,
							"all": 5
						},
						"children": [
							{
								"name": "Номер:",
								"id": "id44374a2e-3f49-4541-f437-de47211af059",
								"isDone": false,
								"comment": "",
								"priority": 0,
								"weight": {
									"done": 0,
									"all": 1
								}
							},
							{
								"name": "Автопроставление при создании справки",
								"id": "id2ea38e32-12dc-4c82-e7e7-be0cf66a44e5",
								"isDone": false,
								"comment": "",
								"priority": 0,
								"weight": {
									"done": 0,
									"all": 1
								}
							},
							{
								"name": "Ограничение на длину",
								"id": "id675a6424-e011-47eb-d28d-360b05239a19",
								"isDone": false,
								"comment": "",
								"priority": 0,
								"weight": {
									"done": 0,
									"all": 1
								}
							},
							{
								"name": "Валидации на корректность",
								"id": "id5aaf0705-1aaa-48c6-342b-191480051914",
								"isDone": false,
								"comment": "",
								"priority": 0,
								"weight": {
									"done": 0,
									"all": 1
								}
							},
							{
								"name": "Валидация на отсутствие",
								"id": "id9ac43386-609d-46e3-db7a-7da5436924fc",
								"isDone": false,
								"comment": "",
								"priority": 0,
								"weight": {
									"done": 0,
									"all": 1
								}
							}
						]
					},
					{
						"name": "Тип:",
						"id": "id46ea4862-ac3e-4fff-e9e7-101ee2e619dd",
						"isDone": false,
						"comment": "",
						"priority": 0,
						"weight": {
							"done": 0,
							"all": 1
						},
						"children": [
							{
								"name": "Автопроставление",
								"id": "id775d904d-51fb-46bb-86f4-289e98872d3b",
								"isDone": false,
								"comment": "",
								"priority": 0,
								"weight": {
									"done": 0,
									"all": 1
								}
							}
						]
					},
					{
						"name": "Номер корректировки:",
						"id": "id574f3673-7d3d-4b2c-2e21-f673161003ae",
						"isDone": false,
						"comment": "",
						"priority": 0,
						"weight": {
							"done": 0,
							"all": 3
						},
						"children": [
							{
								"name": "Автопроставление",
								"id": "id31ffeb67-fa9c-47d7-d8b9-e5eeb6ea4cd3",
								"isDone": false,
								"comment": "",
								"priority": 0,
								"weight": {
									"done": 0,
									"all": 1
								}
							},
							{
								"name": "Запрет ввода некорректных номеров",
								"id": "idfb889ede-887d-43f7-ba91-8dfd7231a896",
								"isDone": false,
								"comment": "",
								"priority": 0,
								"weight": {
									"done": 0,
									"all": 1
								}
							},
							{
								"name": "Валидация на отсутствие",
								"id": "id6a2bb701-d391-4112-bb47-39a56abc6c2f",
								"isDone": false,
								"comment": "",
								"priority": 0,
								"weight": {
									"done": 0,
									"all": 1
								}
							}
						]
					},
					{
						"name": "Печать справок:",
						"id": "id814b3de3-9ff3-44ef-3208-0484826d6765",
						"isDone": false,
						"comment": "",
						"priority": 0,
						"weight": {
							"done": 0,
							"all": 4
						},
						"children": [
							{
								"name": "Печать работает",
								"id": "id1fb86eb5-81e5-4cee-966a-80d70cf296d9",
								"isDone": false,
								"comment": "",
								"priority": 0,
								"weight": {
									"done": 0,
									"all": 1
								}
							},
							{
								"name": "Лайтбокс при печати:",
								"id": "idfdd89585-5f3e-4727-a82e-a923afbe0157",
								"isDone": false,
								"comment": "",
								"priority": 0,
								"weight": {
									"done": 0,
									"all": 1
								}
							},
							{
								"name": "ФИО",
								"id": "id1fcc1f9a-6760-4a6b-f92b-101e713fcfa7",
								"isDone": false,
								"comment": "",
								"priority": 0,
								"weight": {
									"done": 0,
									"all": 1
								}
							},
							{
								"name": "Дата (проставляется)",
								"id": "id43ea8fd6-909d-43ae-8f17-791cd8b6b55f",
								"isDone": false,
								"comment": "",
								"priority": 0,
								"weight": {
									"done": 0,
									"all": 1
								}
							}
						]
					}
				]
			},
			{
				"name": "Удаление справки из карточки",
				"id": "id7a72922a-6f0c-4af1-fb9c-e2a2d6402595",
				"isDone": false,
				"comment": "",
				"priority": 0,
				"weight": {
					"done": 0,
					"all": 1
				}
			},
			{
				"name": "Импорт реквизитов",
				"id": "id97a801a4-12f9-4b1c-3e63-257344cd1ccb",
				"isDone": false,
				"comment": "",
				"priority": 0,
				"weight": {
					"done": 0,
					"all": 1
				}
			},
			{
				"name": "Личные данные Person",
				"id": "id3ca7ab0c-9d7c-4098-7932-dabe2f49fbaf",
				"isDone": false,
				"comment": "",
				"priority": 0,
				"weight": {
					"done": 0,
					"all": 9
				},
				"children": [
					{
						"name": "ФИО",
						"id": "idd7fcf959-b9cb-4a47-2949-e12ef2e6b8ef",
						"isDone": false,
						"comment": "",
						"priority": 0,
						"weight": {
							"done": 0,
							"all": 1
						}
					},
					{
						"name": "ИННФЛ",
						"id": "id12503039-2c50-4fbc-726e-9f38d571eb9b",
						"isDone": false,
						"comment": "",
						"priority": 0,
						"weight": {
							"done": 0,
							"all": 1
						}
					},
					{
						"name": "Дата рождения",
						"id": "id6c08f6cd-7cc6-4182-4ebd-3c3fbb28dda6",
						"isDone": false,
						"comment": "",
						"priority": 0,
						"weight": {
							"done": 0,
							"all": 1
						}
					},
					{
						"name": "Статус налогоплательщика",
						"id": "id19f1ae43-664d-453d-6443-d18d7ad6940c",
						"isDone": false,
						"comment": "",
						"priority": 0,
						"weight": {
							"done": 0,
							"all": 1
						}
					},
					{
						"name": "Гражданство",
						"id": "id33e82a81-2e02-437e-0939-c05864dfaad5",
						"isDone": false,
						"comment": "",
						"priority": 0,
						"weight": {
							"done": 0,
							"all": 1
						}
					},
					{
						"name": "ИНН в стране гражданства",
						"id": "id97120ad9-8b28-46cc-2a1a-c566451f177c",
						"isDone": false,
						"comment": "",
						"priority": 0,
						"weight": {
							"done": 0,
							"all": 1
						}
					},
					{
						"name": "Документ",
						"id": "id12e06c39-546f-46c3-2159-9e25d1d7a94a",
						"isDone": false,
						"comment": "",
						"priority": 0,
						"weight": {
							"done": 0,
							"all": 1
						}
					},
					{
						"name": "Место жительства в РФ",
						"id": "id1b427b34-c4d2-43e5-b97e-96156945d29d",
						"isDone": false,
						"comment": "",
						"priority": 0,
						"weight": {
							"done": 0,
							"all": 1
						}
					},
					{
						"name": "Адрес в стране проживания",
						"id": "id0f03211b-c800-4067-b2d6-c87ee6dc6a70",
						"isDone": false,
						"comment": "",
						"priority": 0,
						"weight": {
							"done": 0,
							"all": 1
						}
					}
				]
			},
			{
				"name": "Доходы по ставке",
				"id": "ide3e8da35-af82-4732-cee8-7ac7acd0b7b3",
				"isDone": false,
				"comment": "",
				"priority": 0,
				"weight": {
					"done": 0,
					"all": 12
				},
				"children": [
					{
						"name": "Ставка",
						"id": "id0910ee09-d51a-4447-ec15-0f6af4d6dbf6",
						"isDone": false,
						"comment": "",
						"priority": 0,
						"weight": {
							"done": 0,
							"all": 2
						},
						"children": [
							{
								"name": "Дивиденды",
								"id": "idcc48cd75-92f0-44dc-0aff-2da8c17ff3ba",
								"isDone": false,
								"comment": "",
								"priority": 0,
								"weight": {
									"done": 0,
									"all": 1
								}
							},
							{
								"name": "#...",
								"id": "id395a905d-2552-4a77-547f-199b5548139f",
								"isDone": false,
								"comment": "",
								"priority": 0,
								"weight": {
									"done": 0,
									"all": 1
								}
							}
						]
					},
					{
						"name": "«Добавить ставку»",
						"id": "id61c452ba-1bf8-45c6-1822-8b209343ffdb",
						"isDone": false,
						"comment": "",
						"priority": 0,
						"weight": {
							"done": 0,
							"all": 1
						}
					},
					{
						"name": "Валидация на отсутствие доходов",
						"id": "id2a5b791a-2ad6-4aa8-62e3-af2a19e29c9d",
						"isDone": false,
						"comment": "",
						"priority": 0,
						"weight": {
							"done": 0,
							"all": 1
						}
					},
					{
						"name": "Доходы по месяцам:",
						"id": "ide8faecd5-f181-418c-7d69-57565b553960",
						"isDone": false,
						"comment": "",
						"priority": 0,
						"weight": {
							"done": 0,
							"all": 7
						},
						"children": [
							{
								"name": "Код дохода",
								"id": "id8a07cda4-5a4b-4f0f-6f0a-36f0afb179b8",
								"isDone": false,
								"comment": "",
								"priority": 0,
								"weight": {
									"done": 0,
									"all": 1
								}
							},
							{
								"name": "Сумма дохода",
								"id": "ida264435a-dbec-438d-7c55-c6dbc23a7367",
								"isDone": false,
								"comment": "",
								"priority": 0,
								"weight": {
									"done": 0,
									"all": 1
								}
							},
							{
								"name": "Удалить код дохода",
								"id": "id4560337e-ad4b-4152-102a-4a3e95760aef",
								"isDone": false,
								"comment": "",
								"priority": 0,
								"weight": {
									"done": 0,
									"all": 1
								}
							},
							{
								"name": "Код вычета",
								"id": "idc2b9f444-692d-470a-d624-3afc180df0f1",
								"isDone": false,
								"comment": "",
								"priority": 0,
								"weight": {
									"done": 0,
									"all": 1
								}
							},
							{
								"name": "Сумма вычета",
								"id": "ida48cc15b-6dc4-427e-8fa0-5bf262129f3a",
								"isDone": false,
								"comment": "",
								"priority": 0,
								"weight": {
									"done": 0,
									"all": 1
								}
							},
							{
								"name": "Добавить код",
								"id": "id59c09210-c614-4f98-868a-8b4ac5a60024",
								"isDone": false,
								"comment": "",
								"priority": 0,
								"weight": {
									"done": 0,
									"all": 1
								}
							},
							{
								"name": "Удалить код вычета",
								"id": "idad0013d8-9335-4bc5-c422-90a8de31b2d2",
								"isDone": false,
								"comment": "",
								"priority": 0,
								"weight": {
									"done": 0,
									"all": 1
								}
							}
						]
					},
					{
						"name": "Вычеты",
						"id": "ideeb34a3e-4912-49e9-03bd-8c518e381666",
						"isDone": false,
						"comment": "",
						"priority": 0,
						"weight": {
							"done": 0,
							"all": 1
						}
					}
				]
			},
			{
				"name": "Вычеты",
				"id": "id3f9d236b-eb98-49b0-bc73-6698320321e9",
				"isDone": false,
				"comment": "",
				"priority": 0,
				"weight": {
					"done": 0,
					"all": 1
				},
				"children": [
					{
						"name": "#...",
						"id": "id9a82000d-48ed-42f2-faf0-db23d9104d43",
						"isDone": false,
						"comment": "",
						"priority": 0,
						"weight": {
							"done": 0,
							"all": 1
						}
					}
				]
			},
			{
				"name": "Общие суммы",
				"id": "id12f7dfcf-80b7-4583-b10e-9b765717ec4b",
				"isDone": false,
				"comment": "",
				"priority": 0,
				"weight": {
					"done": 0,
					"all": 12
				},
				"children": [
					{
						"name": "Рассчёты",
						"id": "ideada1a38-bce4-4532-e8b8-05b39780ce16",
						"isDone": false,
						"comment": "",
						"priority": 0,
						"weight": {
							"done": 0,
							"all": 1
						}
					},
					{
						"name": "Валидации",
						"id": "id6de2ca4a-89b4-4250-04bd-4654a68d7737",
						"isDone": false,
						"comment": "",
						"priority": 0,
						"weight": {
							"done": 0,
							"all": 1
						}
					},
					{
						"name": "Импорт (режим) - лучше в импорте",
						"id": "id859abc00-d859-430a-eda1-0b8f15249f79",
						"isDone": false,
						"comment": "",
						"priority": 0,
						"weight": {
							"done": 0,
							"all": 1
						}
					},
					{
						"name": "Режимы",
						"id": "ideaf9b82e-f0e0-47f3-336d-a667c11e97d6",
						"isDone": false,
						"comment": "",
						"priority": 0,
						"weight": {
							"done": 0,
							"all": 1
						}
					},
					{
						"name": "Поля",
						"id": "id553a0ff2-4090-4de1-360c-b5b438de783a",
						"isDone": false,
						"comment": "",
						"priority": 0,
						"weight": {
							"done": 0,
							"all": 8
						},
						"children": [
							{
								"name": "Общая сумма дохода",
								"id": "idbde916ca-ff77-4630-fb81-4072cfd25339",
								"isDone": false,
								"comment": "",
								"priority": 0,
								"weight": {
									"done": 0,
									"all": 1
								}
							},
							{
								"name": "Налоговая база",
								"id": "idb723dfa4-4899-4ce0-84c2-e151dbef20fb",
								"isDone": false,
								"comment": "",
								"priority": 0,
								"weight": {
									"done": 0,
									"all": 1
								}
							},
							{
								"name": "Исчисленный налог",
								"id": "idb719da0d-4510-42bc-baff-905404ba6afb",
								"isDone": false,
								"comment": "",
								"priority": 0,
								"weight": {
									"done": 0,
									"all": 1
								}
							},
							{
								"name": "Фиксированные авансовые платежи",
								"id": "ida3294d15-45f6-4ec8-bb78-c583b7c84031",
								"isDone": false,
								"comment": "",
								"priority": 0,
								"weight": {
									"done": 0,
									"all": 1
								}
							},
							{
								"name": "Удержанный налог",
								"id": "idbf2b48ed-3603-41ad-dfb7-868cf1e90dc1",
								"isDone": false,
								"comment": "",
								"priority": 0,
								"weight": {
									"done": 0,
									"all": 1
								}
							},
							{
								"name": "Перечисленный налог",
								"id": "id6ab9abba-1f20-4776-8810-eab99755381b",
								"isDone": false,
								"comment": "",
								"priority": 0,
								"weight": {
									"done": 0,
									"all": 1
								}
							},
							{
								"name": "Излишне удержанный",
								"id": "id4d7ed186-4327-449a-dca9-af8c2d982ba7",
								"isDone": false,
								"comment": "",
								"priority": 0,
								"weight": {
									"done": 0,
									"all": 1
								}
							},
							{
								"name": "Не удержанный",
								"id": "idb0691c3a-c191-4787-5678-b3e16fb403cf",
								"isDone": false,
								"comment": "",
								"priority": 0,
								"weight": {
									"done": 0,
									"all": 1
								}
							}
						]
					}
				]
			},
			{
				"name": "Фиксированные авансовые платежи",
				"id": "idd1028a6d-b805-4d21-1c2f-602190965a4a",
				"isDone": false,
				"comment": "",
				"priority": 0,
				"weight": {
					"done": 0,
					"all": 2
				},
				"children": [
					{
						"name": "Наличие в зависимости от ставки",
						"id": "ida752ec86-b7cb-4f51-7fbd-5015f04eaa7c",
						"isDone": false,
						"comment": "",
						"priority": 0,
						"weight": {
							"done": 0,
							"all": 1
						}
					},
					{
						"name": "Валидации",
						"id": "id384d0fc9-6c2a-41ed-d652-4add45e99704",
						"isDone": false,
						"comment": "",
						"priority": 0,
						"weight": {
							"done": 0,
							"all": 1
						}
					}
				]
			}
		]
	},
	{
		"name": "Страница отправки-&gt;SendReportPage",
		"id": "idace21220-e7ee-47bf-1834-69dd2097ebad",
		"isDone": false,
		"comment": "",
		"priority": 0,
		"weight": {
			"done": 0,
			"all": 1
		}
	},
	{
		"name": "Футтер экстерновский-&gt;GlobalFooter",
		"id": "id39541f83-c93a-41c0-5b6a-fecc5ac01188",
		"isDone": false,
		"comment": "",
		"priority": 0,
		"weight": {
			"done": 0,
			"all": 4
		},
		"children": [
			{
				"name": "Ссылки на сервисы",
				"id": "id0509a3ec-1f0c-4674-5c97-d09f4b79ebc8",
				"isDone": false,
				"comment": "",
				"priority": 0,
				"weight": {
					"done": 0,
					"all": 1
				}
			},
			{
				"name": "Время сервера",
				"id": "idcc4d3be1-db9b-431f-30f1-1c5f8a73d62a",
				"isDone": false,
				"comment": "",
				"priority": 0,
				"weight": {
					"done": 0,
					"all": 1
				}
			},
			{
				"name": "О системе",
				"id": "idb5b5bbab-4421-4cc9-7eb1-da7a0c6565d1",
				"isDone": false,
				"comment": "",
				"priority": 0,
				"weight": {
					"done": 0,
					"all": 1
				}
			},
			{
				"name": "Письмо в техподдержку-&gt;SendFeedbackTest",
				"id": "id6af627be-9176-4d84-4b2f-9da8bc2d2f6c",
				"isDone": false,
				"comment": "",
				"priority": 0,
				"weight": {
					"done": 0,
					"all": 1
				}
			}
		]
	},
	{
		"name": "Импорт-&gt;Import",
		"id": "id699ca41c-d56a-468a-77d3-3f3899dfaf7f",
		"isDone": false,
		"comment": "",
		"priority": 0,
		"weight": {
			"done": 0,
			"all": 1
		}
	}
]